docs/source/conf.py
tests/__init__.py
tests/conftest.py
tests/test_calculator.py
tests/test_convert_lammps.py
tests/test_convert_md.py
tests/test_distance.py
tests/test_fingerprint.py
tests/test_msd.py
tests/test_site.py
tests/test_trajectory.py
tests/test_vibration.py
vachoppy/__init__.py
vachoppy/cli.py
vachoppy/core.py
vachoppy/einstein.py
vachoppy/fingerprint.py
vachoppy/frequency.py
vachoppy/main.py
vachoppy/trajectory.py
vachoppy/utils.py
vachoppy/vibration.py
vachoppy-3.0.0.dist-info/licenses/LICENSE
vachoppy-3.0.0.dist-info/METADATA
vachoppy-3.0.0.dist-info/WHEEL
vachoppy-3.0.0.dist-info/entry_points.txt
vachoppy-3.0.0.dist-info/top_level.txt
vachoppy-3.0.0.dist-info/RECORD
