Metadata-Version: 2.4
Name: vachoppy
Version: 3.0.0
Summary: Python package for analyzing vacancy hopping mechanism
Author-email: Taeyoung Jeong <helianthus312@gmail.com>
License: MIT
Keywords: vachoppy,vacancy,hopping
Classifier: Programming Language :: Python :: 3
Classifier: License :: OSI Approved :: MIT License
Classifier: Operating System :: OS Independent
Classifier: Topic :: Scientific/Engineering :: Physics
Requires-Python: >=3.10
License-File: LICENSE
Requires-Dist: ase
Requires-Dist: h5py
Requires-Dist: joblib~=1.5
Requires-Dist: matplotlib>=3.10.0
Requires-Dist: mdanalysis~=2.9
Requires-Dist: numpy~=2.2
Requires-Dist: pandas~=2.3
Requires-Dist: Pillow~=11.3
Requires-Dist: plotly~=6.3
Requires-Dist: pymatgen>=2024.6.10
Requires-Dist: scipy~=1.15
Requires-Dist: tabulate~=0.9
Requires-Dist: tqdm~=4.67
Dynamic: license-file
